<TransactionList>
    <Transaction>
        <Description>Cash withdrawal</Description>
        <Direction>Debit</Direction>
        <Amount>
            <Value>100</Value>
            <Currency>JOD</Currency>
        </Amount>
    </Transaction>
    <Transaction>
        <Description>Salary</Description>
        <Direction>Credit</Direction>
        <Amount>
            <Value>500</Value>
            <Currency>USD</Currency>
        </Amount>
    </Transaction>
    <Transaction>
        <Description>Bill Payment</Description>
        <Direction>Debit</Direction>
        <Amount>
            <Value>10</Value>
            <Currency>JOD</Currency>
        </Amount>
    </Transaction>
</TransactionList>